textregress/__init__.py
textregress/estimator.py
textregress/encoders/__init__.py
textregress/encoders/base.py
textregress/encoders/mock.py
textregress/encoders/registry.py
textregress/encoders/sentence_transformer.py
textregress/encoders/tfidf.py
textregress/losses/__init__.py
textregress/losses/base.py
textregress/losses/registry.py
textregress/losses/regression.py
textregress/models/__init__.py
textregress/models/base.py
textregress/models/gru.py
textregress/models/lstm.py
textregress/models/registry.py
textregress/utils/__init__.py
textregress/utils/dataset.py
textregress/utils/explainability.py
textregress/utils/text.py
textregress-1.3.0.dist-info/licenses/LICENSE
textregress-1.3.0.dist-info/METADATA
textregress-1.3.0.dist-info/WHEEL
textregress-1.3.0.dist-info/top_level.txt
textregress-1.3.0.dist-info/RECORD
