Metadata-Version: 2.4
Name: textregress
Version: 1.3.0
Summary: A package for performing advanced regression on text data using unified deep learning framework.
Author: Jinhang Jiang, Ben Liu, Weiyao Peng, Karthik Srinivasan
Author-email: jinhang@asu.edu
License: MIT License
Project-URL: Homepage, https://github.com/jinhangjiang/textregress
Project-URL: Repository, https://github.com/jinhangjiang/textregress
Keywords: text,predictive nlp,machine learning,nlp,advanced regression,deep learning
Classifier: Development Status :: 5 - Production/Stable
Classifier: Intended Audience :: Science/Research
Classifier: Topic :: Scientific/Engineering :: Artificial Intelligence
Classifier: License :: OSI Approved :: MIT License
Classifier: Programming Language :: Python :: 3
Classifier: Programming Language :: Python :: 3.6
Classifier: Programming Language :: Python :: 3.7
Classifier: Programming Language :: Python :: 3.8
Classifier: Programming Language :: Python :: 3.9
Classifier: Programming Language :: Python :: 3.10
Requires-Python: >=3.6
License-File: LICENSE
Requires-Dist: pandas>=1.5.0
Requires-Dist: numpy>=1.21.0
Requires-Dist: scikit-learn>=1.0.0
Requires-Dist: tqdm>=4.60.0
Requires-Dist: torch>=1.12.0
Requires-Dist: pytorch-lightning>=1.8.0
Requires-Dist: sentence-transformers>=2.0.0
Requires-Dist: transformers>=4.20.0
Requires-Dist: huggingface-hub>=0.10.0
Dynamic: author
Dynamic: author-email
Dynamic: license-file
Dynamic: requires-python
